piff-1.5.1.dist-info/RECORD
piff-1.5.1.dist-info/LICENSE
piff-1.5.1.dist-info/WHEEL
piff-1.5.1.dist-info/top_level.txt
piff-1.5.1.dist-info/METADATA
piff-1.5.1.data/scripts/meanify
piff-1.5.1.data/scripts/piffify
piff-1.5.1.data/scripts/plotify
piff/convolvepsf.py
piff/polynomial_interp.py
piff/readers.py
piff/config.py
piff/_version.py
piff/util.py
piff/knn_interp.py
piff/wavefront.py
piff/size_mag.py
piff/mean_interp.py
piff/star.py
piff/__init__.py
piff/psf.py
piff/writers.py
piff/optical_model.py
piff/model.py
piff/star_stats.py
piff/pixelgrid.py
piff/gsobject_model.py
piff/sumpsf.py
piff/basis_interp.py
piff/outliers.py
piff/stats.py
piff/input.py
piff/simplepsf.py
piff/singlechip.py
piff/select.py
piff/_piff.cpython-311-darwin.so
piff/interp.py
piff/gp_interp.py
piff/meta_data.py
piff/twod_stats.py
piff/output.py
piff/des/__init__.py
piff/des/decam_wavefront.py
piff/des/decaminfo.py
piff/share/DECam_pupil_512uv.fits
piff/share/DECam_pupil_512.fits
piff/share/DECam_pupil_128uv.fits
piff/share/DECam_236392_finegrid512_nm_uv.fits
piff/share/DECam_pupil_128.fits
