Metadata-Version: 2.1
Name: Piff
Version: 1.5.1
Summary: PSFs in the Full FOV
Home-page: https://github.com/rmjarvis/Piff
Download-URL: https://github.com/rmjarvis/Piff/releases/tag/v1.5.1.zip
Author: Mike Jarvis
Author-email: michael@jarvis.net
License: BSD License
License-File: LICENSE
Requires-Dist: galsim>=2.4
Requires-Dist: numpy>=1.17
Requires-Dist: scipy>=1.2
Requires-Dist: pyyaml>=5.1
Requires-Dist: treecorr>=4.3.1
Requires-Dist: fitsio>=1.0
Requires-Dist: matplotlib>=3.6
Requires-Dist: LSSTDESC.Coord>=1.0
Requires-Dist: treegp>=1.3
Requires-Dist: threadpoolctl>=3.1
